libTerm/__init__.py
libTerm/types.py
libTerm/term/__init__.py
libTerm/term/cursor.py
libTerm/term/input.py
libTerm/term/mock.py
libTerm/term/posix.py
libTerm/term/virt.py
libTerm/term/winnt.py
libterm-0.2.5.dist-info/METADATA
libterm-0.2.5.dist-info/WHEEL
libterm-0.2.5.dist-info/top_level.txt
libterm-0.2.5.dist-info/RECORD
