Metadata-Version: 2.4
Name: libTerm
Version: 0.2.5
Author-email: Jeroen Hoefkens <hoefkens.j@gmail.com>
Project-URL: Homepage, https://github.com/hoefkensj/libTerm
Project-URL: Issues, https://github.com/hoefkensj/libTerm
